html5lib-stubs/METADATA.toml
html5lib-stubs/__init__.pyi
html5lib-stubs/_ihatexml.pyi
html5lib-stubs/_inputstream.pyi
html5lib-stubs/_tokenizer.pyi
html5lib-stubs/_utils.pyi
html5lib-stubs/constants.pyi
html5lib-stubs/html5parser.pyi
html5lib-stubs/py.typed
html5lib-stubs/serializer.pyi
html5lib-stubs/_trie/__init__.pyi
html5lib-stubs/_trie/_base.pyi
html5lib-stubs/_trie/py.pyi
html5lib-stubs/filters/__init__.pyi
html5lib-stubs/filters/alphabeticalattributes.pyi
html5lib-stubs/filters/base.pyi
html5lib-stubs/filters/inject_meta_charset.pyi
html5lib-stubs/filters/lint.pyi
html5lib-stubs/filters/optionaltags.pyi
html5lib-stubs/filters/sanitizer.pyi
html5lib-stubs/filters/whitespace.pyi
html5lib-stubs/treeadapters/__init__.pyi
html5lib-stubs/treeadapters/genshi.pyi
html5lib-stubs/treeadapters/sax.pyi
html5lib-stubs/treebuilders/__init__.pyi
html5lib-stubs/treebuilders/base.pyi
html5lib-stubs/treebuilders/dom.pyi
html5lib-stubs/treebuilders/etree.pyi
html5lib-stubs/treebuilders/etree_lxml.pyi
html5lib-stubs/treewalkers/__init__.pyi
html5lib-stubs/treewalkers/base.pyi
html5lib-stubs/treewalkers/dom.pyi
html5lib-stubs/treewalkers/etree.pyi
html5lib-stubs/treewalkers/etree_lxml.pyi
html5lib-stubs/treewalkers/genshi.pyi
types_html5lib-1.1.11.20251115.dist-info/licenses/LICENSE
types_html5lib-1.1.11.20251115.dist-info/METADATA
types_html5lib-1.1.11.20251115.dist-info/WHEEL
types_html5lib-1.1.11.20251115.dist-info/top_level.txt
types_html5lib-1.1.11.20251115.dist-info/RECORD
